aiops_staticfiles/__init__.py
aiops_staticfiles/favicon.png
aiops_staticfiles/index.css
aiops_staticfiles/logo.png
aiops_staticfiles/middleware.js
aiops_staticfiles-1.0.0.dist-info/METADATA
aiops_staticfiles-1.0.0.dist-info/WHEEL
aiops_staticfiles-1.0.0.dist-info/top_level.txt
aiops_staticfiles-1.0.0.dist-info/RECORD
