Metadata-Version: 2.1
Name: aiops-staticfiles
Version: 1.0.0
Summary: AIOPS Portal backend staticfiles
Home-page: UNKNOWN
License: UNKNOWN
Platform: UNKNOWN
Classifier: Programming Language :: Python :: 3
Classifier: Operating System :: OS Independent
Requires-Python: >=3.8
